pyoptmc/__init__.py
pyoptmc/_decorators.py
pyoptmc/dateutil/__init__.py
pyoptmc/dateutil/_china_holidays.py
pyoptmc/dateutil/date.py
pyoptmc/engine/__init__.py
pyoptmc/engine/monte_carlo.py
pyoptmc/model/__init__.py
pyoptmc/model/market_process.py
pyoptmc/products/__init__.py
pyoptmc/products/products.py
pyoptmc/structures/__init__.py
pyoptmc/structures/_docs.py
pyoptmc/structures/asian.py
pyoptmc/structures/autocalls.py
pyoptmc/structures/barrier_options.py
pyoptmc/structures/base.py
pyoptmc/structures/creator/__init__.py
pyoptmc/structures/creator/creator.py
pyoptmc/tools/__init__.py
pyoptmc/tools/helper.py
pyoptmc/tools/payoffs.py
pyoptmc-0.14.2.dist-info/licenses/LICENSE.txt
pyoptmc-0.14.2.dist-info/METADATA
pyoptmc-0.14.2.dist-info/WHEEL
pyoptmc-0.14.2.dist-info/top_level.txt
pyoptmc-0.14.2.dist-info/RECORD
