Metadata-Version: 2.4
Name: pyoptmc
Version: 0.14.2
Summary: A package for pricing OTC options using a vectorized Monte Carlo method.
Home-page: 
Author: Yu Lu
Author-email: luyudso@gmail.com
License: Free for non-commercial use
Keywords: derivatives,finance
Classifier: Development Status :: 3 - Alpha
Classifier: Programming Language :: Python :: 3.8
Requires-Python: >=3.8
License-File: LICENSE.txt
Requires-Dist: numpy
Requires-Dist: joblib>=1.5.2
Requires-Dist: scipy>=1.7.1
Requires-Dist: numba
Dynamic: author
Dynamic: author-email
Dynamic: classifier
Dynamic: description
Dynamic: description-content-type
Dynamic: keywords
Dynamic: license
Dynamic: license-file
Dynamic: requires-dist
Dynamic: requires-python
Dynamic: summary
